sslpsk3/__init__.py
sslpsk3/_sslpsk3.c
sslpsk3/sslpsk3.py
sslpsk3/_sslpsk3_openssl1.cp39-win_amd64.pyd
sslpsk3/_sslpsk3_openssl3.cp39-win_amd64.pyd
sslpsk3-2.0.0.dist-info/LICENSE
sslpsk3-2.0.0.dist-info/METADATA
sslpsk3-2.0.0.dist-info/NOTICE
sslpsk3-2.0.0.dist-info/WHEEL
sslpsk3-2.0.0.dist-info/RECORD
